reloading/__init__.py
reloading/reloading.py
reloading/test_reloading.py
fhreloading-1.1.6.dist-info/METADATA
fhreloading-1.1.6.dist-info/WHEEL
fhreloading-1.1.6.dist-info/RECORD
