Metadata-Version: 2.1
Name: fhreloading
Version: 1.1.6
Summary: Reloads source code of a running program without losing state.
Author: wsd
Author-email: wsd@fhit.cn
Requires-Python: >=3.8,<4.0
Classifier: Programming Language :: Python :: 3
Classifier: Programming Language :: Python :: 3.8
Classifier: Programming Language :: Python :: 3.9
Classifier: Programming Language :: Python :: 3.10
Classifier: Programming Language :: Python :: 3.11
Classifier: Programming Language :: Python :: 3.12
Classifier: Programming Language :: Python :: 3.13
